pysjtu-0.4.2.dist-info/METADATA
pysjtu-0.4.2.dist-info/WHEEL
pysjtu-0.4.2.dist-info/licenses/LICENSE
pysjtu/__init__.py
pysjtu/client/__init__.py
pysjtu/client/api/__init__.py
pysjtu/client/api/course.py
pysjtu/client/api/exam.py
pysjtu/client/api/gpa.py
pysjtu/client/api/profile.py
pysjtu/client/api/schedule.py
pysjtu/client/api/score.py
pysjtu/client/api/selection.py
pysjtu/client/base.py
pysjtu/consts.py
pysjtu/exceptions.py
pysjtu/fields.py
pysjtu/models/__init__.py
pysjtu/models/base.py
pysjtu/models/common.py
pysjtu/models/course.py
pysjtu/models/exam.py
pysjtu/models/gpa.py
pysjtu/models/profile.py
pysjtu/models/schedule.py
pysjtu/models/score.py
pysjtu/models/selection.py
pysjtu/ocr/__init__.py
pysjtu/ocr/nn_model.onnx
pysjtu/ocr/svm_model.onnx
pysjtu/parser/__init__.py
pysjtu/parser/profile.py
pysjtu/parser/selection.py
pysjtu/schema.py
pysjtu/session.py
pysjtu/utils.py
pysjtu-0.4.2.dist-info/RECORD
