Metadata-Version: 2.1
Name: pysjtu
Version: 0.4.2
Summary: The Python iSJTU client for Humans.
Home-page: https://github.com/PhotonQuantum/pysjtu
Author-Email: LightQuantum <self@lightquantum.me>
License: GPL-3.0-or-later
Classifier: Operating System :: OS Independent
Classifier: Environment :: Web Environment
Classifier: Intended Audience :: Developers
Classifier: Topic :: Internet :: WWW/HTTP :: Dynamic Content
Classifier: Topic :: Software Development :: Libraries :: Python Modules
Project-URL: Homepage, https://github.com/PhotonQuantum/pysjtu
Project-URL: Repository, https://github.com/PhotonQuantum/pysjtu
Project-URL: Documentation, https://pysjtu.readthedocs.io/en/latest
Requires-Python: >=3.9
Requires-Dist: marshmallow>=3.21.2
Requires-Dist: lxml>=4.9.2
Requires-Dist: httpx>=0.27.0
Requires-Dist: marshmallow-dataclass>=8.6.1
Requires-Dist: typing-extensions>=4.6.0
Requires-Dist: Sphinx>=4.5.0; extra == "docs"
Requires-Dist: sphinx-book-theme>=0.4.0-rc1; extra == "docs"
Requires-Dist: pytest>=7.2.1; extra == "tests"
Requires-Dist: pytest-cov>=4.0.0; extra == "tests"
Requires-Dist: pytest-mock>=3.10.0; extra == "tests"
Requires-Dist: Flask>=2.2.2; extra == "tests"
Requires-Dist: flake8>=5.0.4; extra == "tests"
Requires-Dist: respx>=0.20.1; extra == "tests"
Requires-Dist: onnxruntime>=1.18.0; extra == "ocr"
Requires-Dist: numpy>=1.26.4; extra == "ocr"
Requires-Dist: Pillow>=10.3.0; extra == "ocr"
Provides-Extra: docs
Provides-Extra: tests
Provides-Extra: ocr
